pymusiccast/__init__.py
pymusiccast/__version__.py
pymusiccast/const.py
pymusiccast/exceptions.py
pymusiccast/helpers.py
pymusiccast/media_status.py
pymusiccast/zone.py
pymusiccast-0.1.6.dist-info/DESCRIPTION.rst
pymusiccast-0.1.6.dist-info/METADATA
pymusiccast-0.1.6.dist-info/RECORD
pymusiccast-0.1.6.dist-info/WHEEL
pymusiccast-0.1.6.dist-info/metadata.json
pymusiccast-0.1.6.dist-info/top_level.txt
