Metadata-Version: 2.0
Name: pymusiccast
Version: 0.1.6
Summary: This library brings support for         Yamaha MusicCast devices to Home Assistant
Home-page: https://github.com/jalmeroth/pymusiccast
Author: Jan Almeroth
Author-email: jan+pymusiccast@almeroth.com
License: MIT
Platform: UNKNOWN
Classifier: Development Status :: 1 - Planning
Classifier: Intended Audience :: Developers
Classifier: Programming Language :: Python :: 3
Classifier: Operating System :: OS Independent
Classifier: Topic :: Home Automation
Requires-Dist: requests (>=2.0)
